pytr/__init__.py
pytr/__main__.py
pytr/account.py
pytr/alarms.py
pytr/api.py
pytr/details.py
pytr/dl.py
pytr/event.py
pytr/main.py
pytr/portfolio.py
pytr/timeline.py
pytr/transactions.py
pytr/translation.py
pytr/utils.py
pytr/locale/.pybabel.info
pytr/locale/cs/LC_MESSAGES/messages.mo
pytr/locale/da/LC_MESSAGES/messages.mo
pytr/locale/de/LC_MESSAGES/messages.mo
pytr/locale/en/LC_MESSAGES/messages.mo
pytr/locale/es/LC_MESSAGES/messages.mo
pytr/locale/fr/LC_MESSAGES/messages.mo
pytr/locale/it/LC_MESSAGES/messages.mo
pytr/locale/nl/LC_MESSAGES/messages.mo
pytr/locale/pl/LC_MESSAGES/messages.mo
pytr/locale/pt/LC_MESSAGES/messages.mo
pytr/locale/ru/LC_MESSAGES/messages.mo
pytr/locale/sk/LC_MESSAGES/messages.mo
pytr/locale/zh/LC_MESSAGES/messages.mo
pytr-0.4.5.dist-info/METADATA
pytr-0.4.5.dist-info/WHEEL
pytr-0.4.5.dist-info/entry_points.txt
pytr-0.4.5.dist-info/licenses/LICENSE
pytr-0.4.5.dist-info/RECORD
