Metadata-Version: 2.4
Name: pytr
Version: 0.4.5
Summary: Use TradeRepublic in terminal
Project-URL: Homepage, https://github.com/pytr-org/pytr
Author-email: marzzzello <853485-marzzzello@users.noreply.gitlab.com>
License: MIT
License-File: LICENSE
Classifier: Development Status :: 3 - Alpha
Classifier: License :: OSI Approved :: MIT License
Classifier: Operating System :: OS Independent
Classifier: Programming Language :: Python :: 3 :: Only
Classifier: Topic :: Office/Business :: Financial
Classifier: Topic :: Office/Business :: Financial :: Investment
Requires-Python: >=3.10
Requires-Dist: babel
Requires-Dist: certifi
Requires-Dist: coloredlogs
Requires-Dist: ecdsa
Requires-Dist: packaging
Requires-Dist: pathvalidate
Requires-Dist: pygments
Requires-Dist: requests-futures
Requires-Dist: shtab
Requires-Dist: websockets>=14
